{
  "created_at": "2025-03-13T02:18:37.271051+00:00",
  "elapsed": 0.154463,
  "encoding": "utf-8",
  "headers": {
    "Cache-Control": "private, no-store",
    "Connection": "keep-alive",
    "Content-Length": "4467",
    "Content-Type": "application/json",
    "Date": "Thu, 13 Mar 2025 02:18:37 GMT",
    "Strict-Transport-Security": "max-age=31536000",
    "Vary": "Origin",
    "X-Content-Type-Options": "nosniff",
    "X-Frame-Options": "DENY",
    "X-XSS-Protection": "1;mode=block"
  },
  "reason": "",
  "request": {
    "body": "",
    "cookies": {
      "TS0193e6a1": "01283c52a47cfa80f04148bab3448e6c760985c5900b07d1a652336c2f96494cb3b6cecaf83e047a899dc87f98769f6acfe9613166"
    },
    "headers": {
      "Accept": "*/*",
      "Accept-Encoding": "gzip, deflate, br",
      "Connection": "keep-alive",
      "Cookie": "TS0193e6a1=01283c52a47cfa80f04148bab3448e6c760985c5900b07d1a652336c2f96494cb3b6cecaf83e047a899dc87f98769f6acfe9613166",
      "User-Agent": "python-requests/2.32.3"
    },
    "method": "GET",
    "url": "https://geocoding.geo.census.gov/geocoder/geographies/coordinates?benchmark=Public_AR_Census2020&format=json&vintage=Census2020_Census2020&x=-158.035291&y=21.34119"
  },
  "status_code": 200,
  "url": "https://geocoding.geo.census.gov/geocoder/geographies/coordinates?benchmark=Public_AR_Census2020&format=json&vintage=Census2020_Census2020&x=-158.035291&y=21.34119",
  "_decoded_content": {
    "result": {
      "geographies": {
        "State Legislative Districts - Upper": [
          {
            "POP100": 67072,
            "GEOID": "15019",
            "CENTLAT": "+21.2999028",
            "AREAWATER": 54831503,
            "STATE": "15",
            "BASENAME": "19",
            "OID": "212904689816440",
            "LSADC": "LU",
            "SLDU": "019",
            "FUNCSTAT": "N",
            "INTPTLAT": "+21.3102673",
            "NAME": "State Senate District 19",
            "OBJECTID": 699,
            "CENTLON": "-158.0070973",
            "LSY": "2018",
            "HU100": 19386,
            "AREALAND": 31559457,
            "INTPTLON": "-158.0086318",
            "MTFCC": "G5210",
            "LDTYP": "O"
          }
        ],
        "States": [
          {
            "STATENS": "01779782",
            "POP100": 1455271,
            "GEOID": "15",
            "CENTLAT": "+21.0508739",
            "AREAWATER": 11777652106,
            "STATE": "15",
            "BASENAME": "Hawaii",
            "STUSAB": "HI",
            "OID": "2749047648128",
            "LSADC": "00",
            "FUNCSTAT": "A",
            "INTPTLAT": "+19.8281671",
            "DIVISION": "9",
            "NAME": "Hawaii",
            "REGION": "4",
            "OBJECTID": 47,
            "CENTLON": "-157.9936887",
            "AREALAND": 16634147166,
            "INTPTLON": "-155.4950421",
            "HU100": 561066,
            "MTFCC": "G4000",
            "UR": "M"
          }
        ],
        "2020 Urban Areas - Corrected": [
          {
            "GEOID": "39889",
            "CENTLAT": "+21.3586724",
            "AREAWATER": 8571102,
            "BASENAME": "Honolulu, HI",
            "OID": "2702132391318100",
            "UA": "39889",
            "LSADC": "67",
            "FUNCSTAT": "S",
            "INTPTLAT": "+21.3587528",
            "NAME": "Honolulu, HI Urban Area",
            "OBJECTID": 2211,
            "CENTLON": "-157.9356309",
            "AREALAND": 375480534,
            "INTPTLON": "-157.9348944",
            "MTFCC": "G3500"
          }
        ],
        "County Subdivisions": [
          {
            "COUSUB": "90270",
            "POP100": 360841,
            "GEOID": "1500390270",
            "CENTLAT": "+21.3676775",
            "AREAWATER": 198861074,
            "STATE": "15",
            "BASENAME": "Ewa",
            "OID": "2769047647888",
            "LSADC": "22",
            "FUNCSTAT": "S",
            "INTPTLAT": "+21.3682481",
            "NAME": "Ewa CCD",
            "OBJECTID": 30370,
            "CENTLON": "-158.0200853",
            "COUSUBCC": "Z5",
            "HU100": 113256,
            "AREALAND": 426595706,
            "INTPTLON": "-158.0214964",
            "MTFCC": "G4040",
            "COUSUBNS": "01935640",
            "UR": "M",
            "COUNTY": "003"
          }
        ],
        "Census Designated Places": [
          {
            "NECTAPCI": "N",
            "POP100": 7825,
            "GEOID": "1507485",
            "CENTLAT": "+21.3417340",
            "AREAWATER": 0,
            "STATE": "15",
            "BASENAME": "Ewa Villages",
            "OID": "2809047647955",
            "LSADC": "57",
            "PLACE": "07485",
            "FUNCSTAT": "S",
            "INTPTLAT": "+21.3417340",
            "NAME": "Ewa Villages CDP",
            "OBJECTID": 26207,
            "PLACECC": "U2",
            "CENTLON": "-158.0389289",
            "CBSAPCI": "N",
            "HU100": 2014,
            "AREALAND": 2920561,
            "INTPTLON": "-158.0389289",
            "PLACENS": "02414016",
            "MTFCC": "G4210",
            "UR": "U"
          }
        ],
        "State Legislative Districts - Lower": [
          {
            "POP100": 39741,
            "GEOID": "15041",
            "CENTLAT": "+21.2878150",
            "SLDL": "041",
            "AREAWATER": 39327082,
            "STATE": "15",
            "BASENAME": "41",
            "OID": "213904689816573",
            "LSADC": "LL",
            "FUNCSTAT": "N",
            "INTPTLAT": "+21.3102673",
            "NAME": "State House District 41",
            "OBJECTID": 2869,
            "CENTLON": "-158.0187320",
            "LSY": "2018",
            "HU100": 12158,
            "AREALAND": 10912427,
            "INTPTLON": "-158.0086318",
            "MTFCC": "G5220",
            "LDTYP": "O"
          }
        ],
        "Counties": [
          {
            "POP100": 1016508,
            "GEOID": "15003",
            "CENTLAT": "+23.8728034",
            "AREAWATER": 4054877012,
            "STATE": "15",
            "BASENAME": "Honolulu",
            "OID": "2759047647837",
            "LSADC": "06",
            "FUNCSTAT": "A",
            "INTPTLAT": "+21.4613654",
            "NAME": "Honolulu County",
            "OBJECTID": 420,
            "CENTLON": "-164.4436095",
            "COUNTYCC": "H6",
            "COUNTYNS": "00365281",
            "AREALAND": 1555612626,
            "INTPTLON": "-158.2019740",
            "HU100": 370665,
            "MTFCC": "G4020",
            "UR": "M",
            "COUNTY": "003"
          }
        ],
        "116th Congressional Districts": [
          {
            "POP100": 729831,
            "GEOID": "1501",
            "CENTLAT": "+21.3239372",
            "CDSESSN": "116",
            "AREAWATER": 456757723,
            "STATE": "15",
            "BASENAME": "1",
            "OID": "211904689807822",
            "LSADC": "C2",
            "FUNCSTAT": "N",
            "INTPTLAT": "+21.3226396",
            "NAME": "Congressional District 1",
            "OBJECTID": 161,
            "CENTLON": "-157.9030923",
            "HU100": 279616,
            "AREALAND": 541344282,
            "INTPTLON": "-157.9059542",
            "CD116": "01",
            "MTFCC": "G5200"
          }
        ],
        "Census Tracts": [
          {
            "POP100": 3973,
            "GEOID": "15003008626",
            "CENTLAT": "+21.3405052",
            "AREAWATER": 0,
            "STATE": "15",
            "BASENAME": "86.26",
            "OID": "2079015504943394",
            "LSADC": "CT",
            "FUNCSTAT": "S",
            "INTPTLAT": "+21.3405052",
            "NAME": "Census Tract 86.26",
            "OBJECTID": 54028,
            "TRACT": "008626",
            "CENTLON": "-158.0407490",
            "HU100": 1079,
            "AREALAND": 2387388,
            "INTPTLON": "-158.0407490",
            "MTFCC": "G5020",
            "UR": "U",
            "COUNTY": "003"
          }
        ],
        "Census Blocks": [
          {
            "SUFFIX": "",
            "POP100": 0,
            "GEOID": "150030086261007",
            "CENTLAT": "+21.3418579",
            "BLOCK": "1007",
            "AREAWATER": 0,
            "STATE": "15",
            "BASENAME": "1007",
            "OID": "210701000464707",
            "LSADC": "BK",
            "INTPTLAT": "+21.3418579",
            "FUNCSTAT": "S",
            "NAME": "Block 1007",
            "OBJECTID": 3249795,
            "TRACT": "008626",
            "CENTLON": "-158.0348031",
            "BLKGRP": "1",
            "AREALAND": 48433,
            "HU100": 0,
            "INTPTLON": "-158.0348031",
            "MTFCC": "G5040",
            "LWBLKTYP": "L",
            "UR": "U",
            "COUNTY": "003"
          }
        ]
      },
      "input": {
        "vintage": {
          "isDefault": true,
          "id": "2020",
          "vintageName": "Census2020_Census2020",
          "vintageDescription": "Census 2020 Vintage - Census 2020 Benchmark"
        },
        "location": {
          "x": -158.035291,
          "y": 21.34119
        },
        "benchmark": {
          "isDefault": false,
          "benchmarkDescription": "Public Address Ranges - Census 2020 Benchmark",
          "id": "2020",
          "benchmarkName": "Public_AR_Census2020"
        }
      }
    }
  }
}