{
  "created_at": "2025-03-12T21:12:38.704130+00:00",
  "elapsed": 0.199121,
  "encoding": "utf-8",
  "headers": {
    "Cache-Control": "private, no-store",
    "Connection": "keep-alive",
    "Content-Length": "3911",
    "Content-Type": "application/json",
    "Date": "Wed, 12 Mar 2025 21:12:38 GMT",
    "Strict-Transport-Security": "max-age=31536000",
    "Vary": "Origin",
    "X-Content-Type-Options": "nosniff",
    "X-Frame-Options": "DENY",
    "X-XSS-Protection": "1;mode=block"
  },
  "reason": "",
  "request": {
    "body": "",
    "cookies": {
      "TS0193e6a1": "01283c52a4a9029dbc31efffc8ed59d167b99eaaf7eaf547f007930dcd00ecd7ecf1baf198f302b775542454ac4de1cfc3919041cd"
    },
    "headers": {
      "Accept": "*/*",
      "Accept-Encoding": "gzip, deflate, br",
      "Connection": "keep-alive",
      "Cookie": "TS0193e6a1=01283c52a4a9029dbc31efffc8ed59d167b99eaaf7eaf547f007930dcd00ecd7ecf1baf198f302b775542454ac4de1cfc3919041cd",
      "User-Agent": "python-requests/2.32.3"
    },
    "method": "GET",
    "url": "https://geocoding.geo.census.gov/geocoder/geographies/coordinates?benchmark=Public_AR_Current&format=json&vintage=Current_Current&x=-75.624291&y=39.83036"
  },
  "status_code": 200,
  "url": "https://geocoding.geo.census.gov/geocoder/geographies/coordinates?benchmark=Public_AR_Current&format=json&vintage=Current_Current&x=-75.624291&y=39.83036",
  "_decoded_content": {
    "result": {
      "geographies": {
        "States": [
          {
            "STATENS": "01779781",
            "GEOID": "10",
            "CENTLAT": "+38.9932570",
            "AREAWATER": "1399219008",
            "STATE": "10",
            "BASENAME": "Delaware",
            "STUSAB": "DE",
            "OID": "27490331618368",
            "LSADC": "00",
            "FUNCSTAT": "A",
            "INTPTLAT": "+38.9985661",
            "DIVISION": "5",
            "NAME": "Delaware",
            "REGION": "3",
            "OBJECTID": 7,
            "CENTLON": "-075.4514104",
            "AREALAND": "5046692231",
            "INTPTLON": "-075.4416440",
            "MTFCC": "G4000"
          }
        ],
        "Combined Statistical Areas": [
          {
            "POP100": "",
            "GEOID": "428",
            "CENTLAT": "+39.7357889",
            "AREAWATER": "3025809373",
            "BASENAME": "Philadelphia-Reading-Camden, PA-NJ-DE-MD",
            "OID": "2619034687908101",
            "LSADC": "M0",
            "FUNCSTAT": "S",
            "INTPTLAT": "+39.7358038",
            "NAME": "Philadelphia-Reading-Camden, PA-NJ-DE-MD CSA",
            "OBJECTID": 134,
            "CSA": "428",
            "CENTLON": "-075.2899501",
            "INTPTLON": "-075.2920685",
            "AREALAND": "19000592318",
            "HU100": "",
            "MTFCC": "G3100"
          }
        ],
        "County Subdivisions": [
          {
            "COUSUB": "92960",
            "GEOID": "1000392960",
            "CENTLAT": "+39.7865911",
            "AREAWATER": "950855",
            "STATE": "10",
            "BASENAME": "Piedmont",
            "OID": "27690331591516",
            "LSADC": "22",
            "FUNCSTAT": "S",
            "INTPTLAT": "+39.7874001",
            "NAME": "Piedmont CCD",
            "OBJECTID": 31262,
            "CENTLON": "-075.6512386",
            "COUSUBCC": "Z5",
            "AREALAND": "102488833",
            "INTPTLON": "-075.6466353",
            "MTFCC": "G4040",
            "COUSUBNS": "01935621",
            "COUNTY": "003"
          }
        ],
        "Counties": [
          {
            "GEOID": "10003",
            "CENTLAT": "+39.5780304",
            "AREAWATER": "175313041",
            "STATE": "10",
            "BASENAME": "New Castle",
            "OID": "27590331579041",
            "LSADC": "06",
            "FUNCSTAT": "A",
            "INTPTLAT": "+39.5759152",
            "NAME": "New Castle County",
            "OBJECTID": 3135,
            "CENTLON": "-075.6390653",
            "COUNTYCC": "H1",
            "COUNTYNS": "00217270",
            "AREALAND": "1104210696",
            "INTPTLON": "-075.6441324",
            "MTFCC": "G4020",
            "COUNTY": "003"
          }
        ],
        "2024 State Legislative Districts - Upper": [
          {
            "GEOID": "10004",
            "CENTLAT": "+39.7919555",
            "AREAWATER": "947909",
            "STATE": "10",
            "BASENAME": "4",
            "OID": "2129035963375331",
            "SLDU": "004",
            "LSADC": "LU",
            "FUNCSTAT": "N",
            "INTPTLAT": "+39.7924767",
            "NAME": "State Senate District 4",
            "OBJECTID": 333,
            "CENTLON": "-075.6319216",
            "LSY": "2024",
            "AREALAND": "114526667",
            "INTPTLON": "-075.6294441",
            "MTFCC": "G5210",
            "LDTYP": "O"
          }
        ],
        "2024 State Legislative Districts - Lower": [
          {
            "GEOID": "10012",
            "CENTLAT": "+39.7961432",
            "SLDL": "012",
            "AREAWATER": "938252",
            "STATE": "10",
            "BASENAME": "12",
            "OID": "2139035963375366",
            "LSADC": "09",
            "FUNCSTAT": "N",
            "INTPTLAT": "+39.7965002",
            "NAME": "State Representative District 12",
            "OBJECTID": 3482,
            "CENTLON": "-075.6081392",
            "LSY": "2024",
            "AREALAND": "88069678",
            "INTPTLON": "-075.6128401",
            "MTFCC": "G5220",
            "LDTYP": "O"
          }
        ],
        "2020 Census Blocks": [
          {
            "SUFFIX": "",
            "GEOID": "100030118004009",
            "CENTLAT": "+39.8303388",
            "BLOCK": "4009",
            "AREAWATER": "0",
            "STATE": "10",
            "BASENAME": "4009",
            "OID": "210701007489934",
            "LSADC": "BK",
            "FUNCSTAT": "S",
            "INTPTLAT": "+39.8303388",
            "NAME": "Block 4009",
            "OBJECTID": 5058563,
            "TRACT": "011800",
            "CENTLON": "-075.6150542",
            "BLKGRP": "4",
            "AREALAND": "1393880",
            "INTPTLON": "-075.6150542",
            "MTFCC": "G5040",
            "LWBLKTYP": "L",
            "UR": "R",
            "COUNTY": "003"
          }
        ],
        "Census Tracts": [
          {
            "GEOID": "10003011800",
            "CENTLAT": "+39.8093367",
            "AREAWATER": "135561",
            "STATE": "10",
            "BASENAME": "118",
            "OID": "20790331626744",
            "LSADC": "CT",
            "FUNCSTAT": "S",
            "INTPTLAT": "+39.8077052",
            "NAME": "Census Tract 118",
            "OBJECTID": 7124,
            "TRACT": "011800",
            "CENTLON": "-075.6121189",
            "AREALAND": "39858016",
            "INTPTLON": "-075.6101476",
            "MTFCC": "G5020",
            "COUNTY": "003"
          }
        ],
        "119th Congressional Districts": [
          {
            "GEOID": "1000",
            "CENTLAT": "+38.9932570",
            "CDSESSN": "119",
            "AREAWATER": "1399219008",
            "BASENAME": "Congressional District (at Large)",
            "STATE": "10",
            "OID": "2119035963374570",
            "LSADC": "C1",
            "FUNCSTAT": "N",
            "INTPTLAT": "+38.9985661",
            "NAME": "Congressional District (at Large)",
            "OBJECTID": 168,
            "CENTLON": "-075.4514104",
            "CD119": "00",
            "AREALAND": "5046692231",
            "INTPTLON": "-075.4416440",
            "MTFCC": "G5200"
          }
        ]
      },
      "input": {
        "vintage": {
          "isDefault": true,
          "id": "4",
          "vintageName": "Current_Current",
          "vintageDescription": "Current Vintage - Current Benchmark"
        },
        "location": {
          "x": -75.624291,
          "y": 39.83036
        },
        "benchmark": {
          "isDefault": true,
          "benchmarkDescription": "Public Address Ranges - Current Benchmark",
          "id": "4",
          "benchmarkName": "Public_AR_Current"
        }
      }
    }
  }
}